nemwriter/__init__.py
nemwriter/nem12_writer.py
nemwriter/nem13_writer.py
nemwriter/py.typed
nemwriter/version.py
nemwriter-0.4.6.dist-info/LICENSE
nemwriter-0.4.6.dist-info/WHEEL
nemwriter-0.4.6.dist-info/METADATA
nemwriter-0.4.6.dist-info/RECORD
