Metadata-Version: 2.1
Name: nemwriter
Version: 0.4.6
Summary: nemwriter
Keywords: energy,NEM12,NEM13
Author-email: Alex Guinman <alex@guinman.id.au>
Requires-Python: >=3.8
Classifier: License :: OSI Approved :: MIT License
Classifier: Programming Language :: Python :: 3
Classifier: Programming Language :: Python :: 3.11
Classifier: Programming Language :: Python :: 3.10
Classifier: Programming Language :: Python :: 3.9
Classifier: Programming Language :: Python :: 3.8
Classifier: Operating System :: OS Independent
Requires-Dist: pandas
Requires-Dist: numpy
Requires-Dist: black ; extra == "dev"
Requires-Dist: flake8 ; extra == "dev"
Requires-Dist: flake8-bugbear ; extra == "dev"
Requires-Dist: pep8-naming ; extra == "dev"
Requires-Dist: flake8-builtins ; extra == "dev"
Requires-Dist: pytest >=2.7.3 ; extra == "test"
Requires-Dist: pytest-cov ; extra == "test"
Requires-Dist: mypy ; extra == "test"
Requires-Dist: nemreader ; extra == "test"
Project-URL: Source, https://github.com/aguinane/nem-writer/
Provides-Extra: dev
Provides-Extra: test
